portage-stubs/METADATA.toml
portage-stubs/__init__.pyi
portage-stubs/versions.pyi
types_portage-0.0.1.dist-info/METADATA
types_portage-0.0.1.dist-info/WHEEL
types_portage-0.0.1.dist-info/top_level.txt
types_portage-0.0.1.dist-info/RECORD
