Metadata-Version: 2.1
Name: types-portage
Version: 0.0.1
Summary: Typing stubs for Portage
Home-page: https://github.com/Tatsh/types-portage
License: MIT
Platform: UNKNOWN
Classifier: Typing :: Typed
